<vector xmlns:android="http://schemas.android.com/apk/res/android"
    xmlns:aapt="http://schemas.android.com/aapt"
    android:width="88dp"
    android:height="88dp"
    android:viewportWidth="88"
    android:viewportHeight="88">
  <group>
    <clip-path
        android:pathData="M44,0L44,0A44,44 0,0 1,88 44L88,44A44,44 0,0 1,44 88L44,88A44,44 0,0 1,0 44L0,44A44,44 0,0 1,44 0z"/>
    <path
        android:pathData="M44,0L44,0A44,44 0,0 1,88 44L88,44A44,44 0,0 1,44 88L44,88A44,44 0,0 1,0 44L0,44A44,44 0,0 1,44 0z"
        android:fillColor="#ffffff"/>
    <path
        android:pathData="M66.548,87.305C66.373,88.658 66.199,90.041 66.019,91.446C65.659,94.279 65.283,97.175 64.923,99.998C64.831,100.749 64.733,101.5 64.635,102.24C63.761,109.08 62.984,115.278 62.629,118.878C62.352,121.66 62.131,123.542 62.028,123.954C61.452,126.093 33.243,129.024 28.162,124.355C27.797,124.031 19.769,71.949 20.664,70.303C20.679,70.277 20.7,70.246 20.72,70.216C20.736,70.195 20.751,70.169 20.772,70.149C20.792,70.123 20.818,70.097 20.844,70.072C20.941,69.969 21.075,69.866 21.229,69.763C21.327,69.696 21.435,69.629 21.553,69.563C21.646,69.506 21.749,69.454 21.857,69.398C21.913,69.372 21.98,69.341 22.037,69.311C22.16,69.254 22.289,69.192 22.428,69.136C22.705,69.017 23.009,68.899 23.343,68.786C23.431,68.755 23.508,68.724 23.6,68.693C23.945,68.57 24.32,68.452 24.721,68.339C24.922,68.282 25.133,68.22 25.344,68.164C25.452,68.133 25.56,68.107 25.668,68.076C25.822,68.035 25.976,67.994 26.136,67.953C26.218,67.932 26.295,67.912 26.372,67.896C26.717,67.814 27.072,67.732 27.437,67.649C27.817,67.567 28.208,67.485 28.609,67.408C29.417,67.243 30.271,67.094 31.176,66.95C31.392,66.914 31.613,66.878 31.834,66.847C32.359,66.77 32.898,66.693 33.449,66.626C33.752,66.585 34.05,66.549 34.359,66.513C34.688,66.472 35.022,66.436 35.362,66.4C35.758,66.358 36.164,66.317 36.57,66.281C36.889,66.251 37.213,66.225 37.542,66.194C38.278,66.137 39.024,66.081 39.79,66.035C41.153,65.952 42.562,65.901 44.012,65.875H44.573C62.892,65.711 67.937,67.757 68.513,68.493C68.544,68.539 68.559,68.699 68.559,68.981C68.611,70.648 67.695,78.295 66.553,87.295L66.548,87.305Z">
      <aapt:attr name="android:fillColor">
        <gradient 
            android:startX="31.073"
            android:startY="124.679"
            android:endX="56.35"
            android:endY="56.839"
            android:type="linear">
          <item android:offset="0" android:color="#FF9E48F0"/>
          <item android:offset="0.32" android:color="#FFB241F6"/>
          <item android:offset="0.72" android:color="#FFC53BFC"/>
          <item android:offset="1" android:color="#FFCD39FF"/>
        </gradient>
      </aapt:attr>
    </path>
    <path
        android:pathData="M66.549,87.305C66.374,88.658 66.199,90.041 66.019,91.446C65.659,94.279 65.284,97.175 64.924,99.998C64.831,100.749 64.733,101.5 64.636,102.24C64.574,102.266 64.507,102.292 64.435,102.307C64.229,102.364 64.029,102.384 63.838,102.374C63.576,102.364 63.345,102.302 63.144,102.23C61.961,101.803 60.701,100.296 60.022,99.386C58.906,99.633 56.973,99.952 55.795,99.509C55.456,99.386 55.049,99.16 54.766,98.728C54.545,98.394 54.458,98.039 54.437,97.725C54.386,96.995 54.684,96.259 54.936,95.74C55.265,95.071 55.708,94.413 56.047,93.945C55.553,92.937 54.751,91.106 54.746,89.82C54.746,89.738 54.746,89.656 54.756,89.584C54.782,89.249 54.885,88.812 55.183,88.432C55.445,88.103 55.774,87.902 56.073,87.794C56.896,87.475 57.945,87.578 58.665,87.691C59.153,87.768 59.626,87.876 60.022,87.974C60.048,87.984 60.074,87.989 60.099,87.995C60.177,88.015 60.249,88.031 60.315,88.051C60.855,87.521 61.714,86.729 62.548,86.195C62.979,85.922 63.566,85.608 64.188,85.541C64.461,85.511 64.785,85.521 65.114,85.649C65.314,85.721 65.484,85.819 65.628,85.932C65.746,86.025 65.849,86.123 65.937,86.22C66.209,86.529 66.415,86.925 66.564,87.311L66.549,87.305Z"
        android:fillColor="#ffffff"/>
    <path
        android:pathData="M66.014,91.446C65.654,94.279 65.279,97.175 64.919,99.998C64.734,100.554 64.466,100.991 64.096,101.099C62.893,101.438 60.547,97.962 60.547,97.962C60.547,97.962 56.5,99.073 55.811,98.034C55.543,97.638 55.728,96.969 56.063,96.295C56.603,95.195 57.523,94.074 57.523,94.074C57.523,94.074 55.872,91.06 56.006,89.671C56.027,89.481 56.078,89.327 56.171,89.203C56.526,88.756 57.503,88.776 58.454,88.926H58.47C58.912,88.998 59.349,89.09 59.714,89.188C60.285,89.332 60.696,89.466 60.696,89.466C60.696,89.466 62.018,88.021 63.227,87.249C63.782,86.894 64.312,86.683 64.682,86.822C65.104,86.977 65.387,87.609 65.577,88.365C65.592,88.406 65.603,88.452 65.613,88.494C65.932,89.815 65.983,91.425 65.983,91.425C65.983,91.425 65.999,91.435 66.035,91.446H66.014Z">
      <aapt:attr name="android:fillColor">
        <gradient 
            android:startX="66.055"
            android:startY="84.066"
            android:endX="57.05"
            android:endY="101.325"
            android:type="linear">
          <item android:offset="0.03" android:color="#FFFFC700"/>
          <item android:offset="1" android:color="#FFFF9200"/>
        </gradient>
      </aapt:attr>
    </path>
    <path
        android:pathData="M62.62,118.878C62.342,121.66 62.121,123.548 62.018,123.959C61.442,126.093 33.233,129.025 28.157,124.36C27.787,124.036 19.759,71.954 20.659,70.309C21.544,68.704 26.645,68.884 39.569,68.678C34.905,70.149 24.773,110.084 39.955,121.429C49.901,128.865 61.067,123.26 62.625,118.878H62.62Z"
        android:strokeAlpha="0.4"
        android:fillAlpha="0.4">
      <aapt:attr name="android:fillColor">
        <gradient 
            android:startX="31.012"
            android:startY="124.839"
            android:endX="52.344"
            android:endY="67.599"
            android:type="linear">
          <item android:offset="0" android:color="#FF85007B"/>
          <item android:offset="1" android:color="#FF9F6DCE"/>
        </gradient>
      </aapt:attr>
    </path>
    <path
        android:pathData="M68.554,68.992C64.754,69.877 58.011,70.849 47.381,71.291C29.386,72.026 20.659,70.303 20.659,70.303C21.559,68.668 31.361,66.019 44.568,65.886C62.882,65.721 67.932,67.768 68.508,68.508C68.539,68.555 68.554,68.714 68.554,68.992Z"
        android:fillColor="#DFABFF"/>
    <path
        android:pathData="M65.181,68.39C65.268,68.863 63.679,69.228 61.411,69.511C59.688,69.732 57.554,69.881 55.461,70.01C54.386,70.067 53.326,70.128 52.339,70.17C50.544,70.242 48.955,70.303 47.967,70.344C46.759,70.391 44.167,70.447 41.163,70.447H40.279C36.509,70.447 32.241,70.36 29.294,70.092C26.938,69.902 25.421,69.593 25.627,69.12C25.817,68.663 26.979,68.267 28.779,67.958C31.402,67.5 35.419,67.192 39.836,67.032C40.294,67.017 40.762,67.001 41.235,66.986C42.074,66.955 42.927,66.929 43.781,66.914C46.198,66.883 48.641,66.883 50.95,66.914C51.552,66.914 52.143,66.929 52.719,66.945C53.738,66.96 54.72,66.991 55.651,67.032C58.094,67.135 60.259,67.284 61.894,67.49C63.879,67.711 65.103,68.02 65.175,68.39H65.181Z"
        android:fillColor="#833CC7"
        android:fillType="evenOdd"/>
    <group>
      <clip-path
          android:pathData="M65.181,68.39C65.268,68.863 63.679,69.228 61.411,69.511C59.688,69.732 57.554,69.882 55.461,70.01C54.386,70.067 53.327,70.128 52.339,70.17C50.544,70.242 48.955,70.303 47.968,70.344C46.759,70.391 44.167,70.447 41.164,70.447H40.279C36.509,70.447 32.241,70.36 29.294,70.092C26.939,69.902 25.421,69.593 25.627,69.12C25.817,68.663 12.929,15.712 14.724,15.403C16.097,15.161 28.327,-12.096 45.381,-16.457C60.83,-20.407 81.273,-1.517 82.05,-1.419C84.04,-1.198 65.104,68.02 65.176,68.385L65.181,68.39Z"/>
      <path
          android:pathData="M55.187,29.346C56.004,37.302 49.967,38.238 48.63,38.685C47.292,39.133 45.616,38.49 45.616,38.49C44.515,38.49 38.591,33.558 38.827,27.88C39.084,22.202 45.271,16.674 45.924,14.118C46.397,12.302 46.423,11.186 46.372,10.538C46.326,9.967 46.228,9.787 46.351,9.829C47.102,10.132 48.501,11.145 48.48,14.015C48.486,14.061 48.48,14.092 48.48,14.102C48.527,13.886 48.568,12.4 48.234,11.356C48.084,10.898 50.651,12.328 50.861,16.489C50.964,18.376 52.867,21.169 54.132,24.774C54.132,24.774 54.132,24.789 54.132,24.805C54.631,26.193 55.022,27.715 55.181,29.346H55.187Z"
          android:fillType="evenOdd">
        <aapt:attr name="android:fillColor">
          <gradient 
              android:startX="47.154"
              android:startY="34.926"
              android:endX="46.619"
              android:endY="7.988"
              android:type="linear">
            <item android:offset="0" android:color="#FF94054F"/>
            <item android:offset="1" android:color="#FFFF3B00"/>
          </gradient>
        </aapt:attr>
      </path>
      <path
          android:pathData="M55.187,29.346C56.005,37.302 49.967,38.238 48.63,38.686C47.292,39.133 45.616,38.49 45.616,38.49C44.515,38.49 38.591,33.558 38.827,27.88C39.084,22.203 45.271,16.674 45.924,14.118C46.398,12.303 46.423,11.187 46.372,10.539C46.783,11.644 48.691,14.262 47.529,15.224C43.512,18.541 40.272,21.524 39.748,25.052C39.223,28.585 42.561,37.071 50.748,34.947C57.038,33.316 54.261,25.288 54.132,24.8C54.631,26.188 55.022,27.711 55.182,29.341L55.187,29.346Z"
          android:strokeAlpha="0.4"
          android:fillType="evenOdd"
          android:fillAlpha="0.4">
        <aapt:attr name="android:fillColor">
          <gradient 
              android:startX="38.439"
              android:startY="25.843"
              android:endX="54.452"
              android:endY="23.715"
              android:type="linear">
            <item android:offset="0" android:color="#FF85007B"/>
            <item android:offset="1" android:color="#FF9F6DCE"/>
          </gradient>
        </aapt:attr>
      </path>
      <path
          android:pathData="M48.234,11.361C48.234,11.361 49.396,13.192 49.175,14.956C48.954,16.72 47.653,17.471 46.732,20.809C45.817,24.146 47.046,26.913 47.046,26.913C47.046,26.913 44.608,22.866 45.416,20.86C46.223,18.854 49.046,16.036 48.229,11.361H48.234Z"
          android:strokeAlpha="0.4"
          android:fillType="evenOdd"
          android:fillAlpha="0.4">
        <aapt:attr name="android:fillColor">
          <gradient 
              android:startX="44.917"
              android:startY="19.498"
              android:endX="49.821"
              android:endY="18.846"
              android:type="linear">
            <item android:offset="0" android:color="#FF85007B"/>
            <item android:offset="1" android:color="#FF9F6DCE"/>
          </gradient>
        </aapt:attr>
      </path>
      <path
          android:pathData="M50.096,41.21C50.096,41.21 50.096,41.226 50.096,41.241C50.389,43.458 50.702,46.713 50.944,51.316C51.011,52.612 51.083,54.032 51.14,55.569C51.186,57.035 51.232,58.604 51.278,60.291C51.453,67.295 50.908,76.856 50.06,85.66C49.957,86.771 49.833,87.872 49.71,88.962C49.643,89.672 49.566,90.345 49.494,91.024C47.817,91.472 45.719,91.899 43.662,92.305C43.595,91.348 43.523,90.351 43.461,89.332C42.87,80.96 42.335,70.587 42.253,60.023C42.15,47.845 43.965,40.712 45.04,38.294C45.266,37.76 45.477,37.451 45.601,37.374C46.29,36.973 48.491,37.199 49.098,37.297C49.144,37.307 49.175,37.297 49.206,37.312C49.299,37.328 49.448,37.667 49.617,38.402C49.725,38.891 49.859,39.56 49.977,40.449C50.024,40.696 50.06,40.943 50.096,41.221V41.21Z"
          android:fillType="evenOdd">
        <aapt:attr name="android:fillColor">
          <gradient 
              android:startX="46.389"
              android:startY="83.121"
              android:endX="46.908"
              android:endY="54.196"
              android:type="linear">
            <item android:offset="0" android:color="#FFE66300"/>
            <item android:offset="0.3" android:color="#FFE66700"/>
            <item android:offset="1" android:color="#FFE66F00"/>
          </gradient>
        </aapt:attr>
      </path>
      <path
          android:pathData="M51.279,60.285C50.333,61.319 47.201,61.438 44.876,61.062L44.706,61.026L43.924,60.861C43.081,60.646 42.449,60.357 42.253,60.013C41.98,59.529 41.811,54.232 42.963,46.014C43.77,40.367 44.866,37.071 45.483,36.813C46.63,36.289 48.142,36.577 49.222,37.014C49.628,37.184 49.983,37.359 50.224,37.533C51.109,38.161 52.143,59.334 51.274,60.285H51.279Z"
          android:fillType="evenOdd">
        <aapt:attr name="android:fillColor">
          <gradient 
              android:startX="32.622"
              android:startY="52.256"
              android:endX="63.623"
              android:endY="45.287"
              android:type="linear">
            <item android:offset="0" android:color="#FF736173"/>
            <item android:offset="0.17" android:color="#FF756477"/>
            <item android:offset="0.36" android:color="#FF7E6D84"/>
            <item android:offset="0.55" android:color="#FF8C7D9B"/>
            <item android:offset="0.75" android:color="#FF9F93BA"/>
            <item android:offset="0.96" android:color="#FFB8B0E1"/>
            <item android:offset="1" android:color="#FFBEB7EB"/>
          </gradient>
        </aapt:attr>
      </path>
      <path
          android:pathData="M49.227,37.019C49.191,37.096 49.145,37.194 49.098,37.287C48.903,37.698 48.666,38.176 48.414,38.732C47.895,39.853 47.278,41.257 46.696,42.779C45.503,45.772 44.382,49.28 44.11,52.242C43.477,59.01 44.881,61.067 44.881,61.067L44.711,61.031L43.93,60.867C43.93,60.867 43.102,86.509 50.06,85.66C49.957,86.771 49.834,87.872 49.71,88.962C49.643,89.672 49.566,90.346 49.494,91.024C47.818,91.472 45.719,91.899 43.662,92.305C43.595,91.348 43.523,90.351 43.462,89.332C42.87,80.96 42.335,70.587 42.253,60.023C41.98,59.54 41.811,54.243 42.963,46.024C43.493,42.301 44.161,39.596 44.716,38.109C44.999,37.343 45.272,36.906 45.483,36.819C46.63,36.294 48.142,36.582 49.222,37.019H49.227Z"
          android:strokeAlpha="0.4"
          android:fillType="evenOdd"
          android:fillAlpha="0.4">
        <aapt:attr name="android:fillColor">
          <gradient 
              android:startX="27.518"
              android:startY="68.389"
              android:endX="69.945"
              android:endY="58.855"
              android:type="linear">
            <item android:offset="0" android:color="#FF85007B"/>
            <item android:offset="1" android:color="#FF9F6DCE"/>
          </gradient>
        </aapt:attr>
      </path>
      <path
          android:pathData="M38.874,40.951C38.874,40.951 38.73,40.453 38.489,39.65C38.154,38.514 37.63,36.77 37.059,34.981C36.807,34.194 36.55,33.397 36.293,32.641C35.552,30.419 34.837,28.521 34.462,28.115C34.025,27.642 32.821,27.626 31.741,27.827C30.836,27.992 30.008,28.305 29.787,28.634C29.339,29.298 28.784,32.569 28.321,35.773C28.121,37.182 27.941,38.581 27.797,39.733C27.596,41.358 27.462,42.5 27.462,42.5L38.869,40.951H38.874Z">
        <aapt:attr name="android:fillColor">
          <gradient 
              android:startX="29.729"
              android:startY="21.318"
              android:endX="42.084"
              android:endY="93.891"
              android:type="linear">
            <item android:offset="0" android:color="#FF447ED4"/>
            <item android:offset="0.17" android:color="#FF4375D4"/>
            <item android:offset="0.66" android:color="#FF4362D5"/>
            <item android:offset="1" android:color="#FF435BD6"/>
          </gradient>
        </aapt:attr>
      </path>
      <path
          android:pathData="M38.874,40.952C38.874,40.952 38.73,40.453 38.489,39.651C38.154,38.514 37.63,36.771 37.059,34.981C36.807,34.194 36.55,33.397 36.293,32.641C36.293,32.641 33.886,34.96 31.787,33.5C29.849,32.147 30.044,28.773 31.741,27.827C30.836,27.992 30.008,28.305 29.787,28.635C29.339,29.298 28.784,32.569 28.321,35.773C28.121,37.182 27.941,38.581 27.797,39.733C27.596,41.358 27.462,42.5 27.462,42.5L38.869,40.952H38.874Z"
          android:strokeAlpha="0.2"
          android:fillAlpha="0.2">
        <aapt:attr name="android:fillColor">
          <gradient 
              android:startX="35.357"
              android:startY="21.028"
              android:endX="33.864"
              android:endY="35.399"
              android:type="linear">
            <item android:offset="0" android:color="#FF85007B"/>
            <item android:offset="1" android:color="#FF9F6DCE"/>
          </gradient>
        </aapt:attr>
      </path>
      <path
          android:pathData="M38.489,39.656C38.155,38.519 37.631,36.776 37.06,34.986C36.211,34.549 34.756,34.147 32.39,34.358C30.281,34.549 29.057,35.161 28.322,35.773C28.121,37.182 27.941,38.581 27.797,39.733C31.449,39.722 38.016,39.661 38.484,39.656H38.489Z"
          android:strokeAlpha="0.6"
          android:fillAlpha="0.6">
        <aapt:attr name="android:fillColor">
          <gradient 
              android:startX="32.119"
              android:startY="33.041"
              android:endX="33.928"
              android:endY="44.409"
              android:type="linear">
            <item android:offset="0" android:color="#FF000287"/>
            <item android:offset="1" android:color="#FF9F6DCE"/>
          </gradient>
        </aapt:attr>
      </path>
      <path
          android:pathData="M49.782,99.369C49.438,97.158 49.088,94.916 48.733,92.627C48.543,91.434 48.353,90.225 48.162,89.001C47.926,87.469 47.679,85.916 47.432,84.332C47.298,83.498 47.165,82.655 47.031,81.807C46.748,80.048 46.465,78.248 46.167,76.396C45.18,70.235 44.094,63.539 42.845,56.02C42.577,54.431 42.31,52.801 42.027,51.14C41.888,50.291 41.744,49.437 41.605,48.568C41.42,47.478 41.235,46.377 41.045,45.251C40.916,44.474 40.782,43.698 40.649,42.906C40.463,41.805 40.273,40.684 40.083,39.548C39.985,39.002 39.898,38.457 39.8,37.907C39.389,35.479 25.621,36.647 25.657,39.835C25.657,40.463 25.673,41.09 25.683,41.708C25.688,42.762 25.703,43.796 25.714,44.819C25.739,46.902 25.75,48.923 25.77,50.882C25.775,51.587 25.781,52.286 25.786,52.976C25.801,54.832 25.811,56.632 25.827,58.381C25.873,66.249 25.878,73.064 25.878,78.916C25.878,81.035 25.878,83.02 25.868,84.892C25.868,85.602 25.868,86.286 25.868,86.96C25.858,88.878 25.858,90.647 25.858,92.283C25.858,93.116 25.858,93.908 25.853,94.669C25.853,97.451 25.868,99.791 25.894,101.73C25.894,101.802 25.899,101.869 25.909,101.941C25.909,101.946 25.909,101.951 25.909,101.951C26.13,103.828 28.866,104.708 32.415,104.872C39.455,105.196 49.695,102.707 49.813,99.632C49.813,99.539 49.813,99.452 49.793,99.359L49.782,99.369Z">
        <aapt:attr name="android:fillColor">
          <gradient 
              android:startX="25.561"
              android:startY="23.145"
              android:endX="45.312"
              android:endY="147.349"
              android:type="linear">
            <item android:offset="0" android:color="#FF447ED4"/>
            <item android:offset="0.17" android:color="#FF4375D4"/>
            <item android:offset="0.66" android:color="#FF4362D5"/>
            <item android:offset="1" android:color="#FF435BD6"/>
          </gradient>
        </aapt:attr>
      </path>
      <path
          android:pathData="M25.842,94.684C25.842,93.923 25.842,93.126 25.847,92.298C25.847,90.658 25.847,88.888 25.857,86.98C25.857,86.296 25.857,85.617 25.857,84.908C25.857,84.589 25.857,84.265 25.857,83.936C25.857,82.352 25.862,80.691 25.862,78.932C25.862,73.074 25.862,66.265 25.811,58.391C25.801,56.637 25.791,54.837 25.775,52.986C25.775,52.461 25.765,51.932 25.765,51.402C25.765,51.232 25.765,51.063 25.765,50.893C25.765,50.476 25.754,50.065 25.754,49.648C25.734,48.085 25.724,46.48 25.703,44.829C25.693,43.806 25.683,42.772 25.672,41.718C27.94,40.664 31.129,39.445 34.204,39.167C36.961,38.92 38.848,39.193 40.072,39.558C40.257,40.694 40.448,41.816 40.638,42.916C40.772,43.708 40.911,44.49 41.034,45.261C41.147,45.961 41.265,46.645 41.384,47.329C41.456,47.75 41.523,48.167 41.6,48.578C41.697,49.185 41.795,49.792 41.898,50.384C41.939,50.646 41.985,50.898 42.021,51.15C42.304,52.811 42.577,54.441 42.839,56.03C44.089,63.549 45.174,70.251 46.161,76.412C46.465,78.248 46.748,80.043 47.025,81.781V81.817C47.164,82.665 47.298,83.514 47.432,84.347C47.679,85.931 47.925,87.484 48.157,89.012C48.347,90.241 48.537,91.444 48.728,92.643C46.84,91.902 42.957,90.838 37.059,91.295C31.088,91.768 27.498,93.599 25.842,94.695V94.684Z">
        <aapt:attr name="android:fillColor">
          <gradient 
              android:startX="18.18"
              android:startY="54.58"
              android:endX="48.118"
              android:endY="80.055"
              android:type="linear">
            <item android:offset="0" android:color="#FF69A3F9"/>
            <item android:offset="0.17" android:color="#FF689AF9"/>
            <item android:offset="0.66" android:color="#FF6887FA"/>
            <item android:offset="1" android:color="#FF6880FB"/>
          </gradient>
        </aapt:attr>
      </path>
      <path
          android:pathData="M25.858,83.93C25.858,82.346 25.863,80.685 25.863,78.926C25.863,73.068 25.863,66.259 25.812,58.386C25.801,56.632 25.791,54.832 25.776,52.98C25.776,52.456 25.765,51.926 25.765,51.396C27.416,52.086 30.553,55.115 30.198,68.101C29.89,79.286 27.462,82.819 25.863,83.93H25.858Z">
        <aapt:attr name="android:fillColor">
          <gradient 
              android:startX="35.563"
              android:startY="67.384"
              android:endX="16.899"
              android:endY="67.988"
              android:type="linear">
            <item android:offset="0" android:color="#FF4F1388"/>
            <item android:offset="0.12" android:color="#FF531C93"/>
            <item android:offset="0.49" android:color="#FF5F38B4"/>
            <item android:offset="0.79" android:color="#FF6748C7"/>
            <item android:offset="1" android:color="#FF6A4FCF"/>
          </gradient>
        </aapt:attr>
      </path>
      <path
          android:pathData="M41.39,47.319C41.277,46.635 41.153,45.945 41.04,45.251C40.912,44.475 40.778,43.698 40.644,42.906C39.019,42.33 36.324,41.816 32.611,42.577C29.289,43.256 27.072,44.13 25.709,44.824C25.73,46.47 25.74,48.08 25.761,49.643C29.139,47.725 38.546,46.825 41.395,47.319H41.39Z">
        <aapt:attr name="android:fillColor">
          <gradient 
              android:startX="25.494"
              android:startY="46.398"
              android:endX="41.209"
              android:endY="44.981"
              android:type="linear">
            <item android:offset="0" android:color="#FF4F1388"/>
            <item android:offset="0.12" android:color="#FF531C93"/>
            <item android:offset="0.49" android:color="#FF5F38B4"/>
            <item android:offset="0.79" android:color="#FF6748C7"/>
            <item android:offset="1" android:color="#FF6A4FCF"/>
          </gradient>
        </aapt:attr>
      </path>
      <path
          android:pathData="M41.04,45.251C40.639,42.88 40.227,40.437 39.795,37.907C39.384,35.479 25.616,36.647 25.652,39.835C26.038,72.961 25.755,92.216 25.884,101.745C25.914,103.777 28.722,104.718 32.405,104.888C29.432,90.786 27.828,44.207 32.456,40.895C37.435,37.326 40.865,44.855 41.04,45.251Z"
          android:strokeAlpha="0.4"
          android:fillAlpha="0.4">
        <aapt:attr name="android:fillColor">
          <gradient 
              android:startX="37.377"
              android:startY="4.074"
              android:endX="30.583"
              android:endY="69.403"
              android:type="linear">
            <item android:offset="0" android:color="#FF85007B"/>
            <item android:offset="1" android:color="#FF9F6DCE"/>
          </gradient>
        </aapt:attr>
      </path>
      <path
          android:pathData="M42.145,80.022C36.884,80.634 36.817,64.681 40.808,65.159C44.799,65.642 45.827,79.59 42.145,80.022Z"
          android:strokeAlpha="0.5"
          android:fillColor="#AED98A"
          android:fillAlpha="0.5"/>
      <path
          android:pathData="M40.072,62.768C38.91,62.994 39.219,59.06 40.268,60.289C41.317,61.518 40.993,62.588 40.072,62.768Z"
          android:strokeAlpha="0.5"
          android:fillColor="#AED98A"
          android:fillAlpha="0.5"/>
      <path
          android:pathData="M68.473,49.753C68.128,51.779 67.784,53.837 67.429,55.935C67.243,57.03 67.053,58.136 66.863,59.257C66.626,60.661 66.385,62.086 66.138,63.536C66.004,64.297 65.876,65.074 65.742,65.85C65.464,67.46 65.181,69.116 64.888,70.808C63.916,76.455 62.841,82.595 61.617,89.487C61.355,90.942 61.093,92.439 60.815,93.961C60.676,94.738 60.537,95.525 60.398,96.317C60.218,97.314 60.033,98.322 59.853,99.356C59.73,100.066 59.596,100.781 59.467,101.506C59.287,102.514 59.102,103.542 58.917,104.581C58.825,105.08 58.737,105.579 58.645,106.083C58.243,108.305 47.629,106.669 47.768,103.728C47.793,103.146 47.824,102.565 47.85,102C47.891,101.028 47.937,100.071 47.978,99.125C48.071,97.201 48.148,95.34 48.23,93.529C48.256,92.881 48.287,92.233 48.313,91.595C48.39,89.883 48.457,88.222 48.529,86.607C48.832,79.34 49.074,73.05 49.269,67.645C49.341,65.686 49.408,63.855 49.465,62.127C49.49,61.469 49.511,60.841 49.537,60.219C49.593,58.45 49.655,56.814 49.711,55.302C49.737,54.531 49.768,53.801 49.789,53.096C49.886,50.525 49.974,48.365 50.061,46.58C50.061,46.513 50.071,46.451 50.077,46.39C50.077,46.384 50.077,46.379 50.077,46.379C50.313,44.651 52.458,43.957 55.214,43.952C60.676,43.937 68.514,46.657 68.498,49.501C68.498,49.589 68.488,49.666 68.473,49.753Z">
        <aapt:attr name="android:fillColor">
          <gradient 
              android:startX="45.592"
              android:startY="119.042"
              android:endX="68.782"
              android:endY="5.724"
              android:type="linear">
            <item android:offset="0" android:color="#FFF56CC0"/>
            <item android:offset="0.28" android:color="#FFF849AF"/>
            <item android:offset="0.58" android:color="#FFFC289F"/>
            <item android:offset="0.83" android:color="#FFFE1596"/>
            <item android:offset="1" android:color="#FFFF0E93"/>
          </gradient>
        </aapt:attr>
      </path>
      <path
          android:pathData="M67.429,55.935C67.244,57.03 67.053,58.136 66.863,59.257C66.627,60.661 66.385,62.086 66.138,63.536C66.004,64.297 65.876,65.074 65.742,65.85V65.881C65.464,67.481 65.181,69.121 64.888,70.808C63.916,76.455 62.841,82.595 61.617,89.487C61.355,90.942 61.093,92.439 60.815,93.961C60.774,94.193 60.733,94.424 60.692,94.661C60.594,95.206 60.501,95.761 60.398,96.317C60.326,96.697 60.265,97.078 60.193,97.464C60.08,98.091 59.966,98.718 59.853,99.356C59.73,100.066 59.596,100.781 59.468,101.506C59.288,102.514 59.103,103.542 58.917,104.581C57.961,104.869 56.49,105.044 54.366,104.705C51.99,104.324 49.568,103.069 47.845,102C47.886,101.028 47.932,100.071 47.973,99.125C48.045,97.607 48.107,96.121 48.179,94.676C48.189,94.29 48.21,93.91 48.225,93.524C48.251,92.876 48.282,92.228 48.308,91.59C48.385,89.878 48.452,88.217 48.524,86.602C48.827,79.335 49.069,73.045 49.264,67.64C49.336,65.681 49.403,63.85 49.46,62.122C49.485,61.463 49.506,60.836 49.532,60.214C49.588,58.445 49.65,56.809 49.706,55.297C49.732,54.526 49.763,53.795 49.784,53.091C51.028,54.171 53.744,56.012 58.352,56.686C62.903,57.354 65.942,56.526 67.429,55.924V55.935Z">
        <aapt:attr name="android:fillColor">
          <gradient 
              android:startX="47.74"
              android:startY="78.486"
              android:endX="60.732"
              android:endY="79.931"
              android:type="linear">
            <item android:offset="0" android:color="#FFFF4EB3"/>
            <item android:offset="0.12" android:color="#FFFF5AB9"/>
            <item android:offset="0.49" android:color="#FFFF7BCA"/>
            <item android:offset="0.79" android:color="#FFFF8ED5"/>
            <item android:offset="1" android:color="#FFFF96D9"/>
          </gradient>
        </aapt:attr>
      </path>
      <path
          android:pathData="M54.068,92.593C56.398,92.603 58.542,88.72 59.231,80.862C59.833,74.022 58.074,63.963 54.438,65.799C50.807,67.635 47.223,92.562 54.063,92.593H54.068Z">
        <aapt:attr name="android:fillColor">
          <gradient 
              android:startX="49.891"
              android:startY="78.311"
              android:endX="59.868"
              android:endY="80.073"
              android:type="linear">
            <item android:offset="0" android:color="#FF4F1388"/>
            <item android:offset="0.12" android:color="#FF531C93"/>
            <item android:offset="0.49" android:color="#FF5F38B4"/>
            <item android:offset="0.79" android:color="#FF6748C7"/>
            <item android:offset="1" android:color="#FF6A4FCF"/>
          </gradient>
        </aapt:attr>
      </path>
      <path
          android:pathData="M66.864,59.262C66.627,60.661 66.385,62.086 66.139,63.536C64.364,64.297 61.402,64.976 57.339,63.922C53.364,62.888 50.911,61.35 49.532,60.219C49.589,58.45 49.651,56.814 49.707,55.302C51.615,57.015 54.917,59.303 59.592,59.879C62.796,60.27 65.357,60.023 66.864,59.257V59.262Z">
        <aapt:attr name="android:fillColor">
          <gradient 
              android:startX="49.181"
              android:startY="59.147"
              android:endX="66.556"
              android:endY="61.49"
              android:type="linear">
            <item android:offset="0" android:color="#FF4F1388"/>
            <item android:offset="0.12" android:color="#FF531C93"/>
            <item android:offset="0.49" android:color="#FF5F38B4"/>
            <item android:offset="0.79" android:color="#FF6748C7"/>
            <item android:offset="1" android:color="#FF6A4FCF"/>
          </gradient>
        </aapt:attr>
      </path>
      <path
          android:pathData="M59.854,99.361C59.463,101.532 59.062,103.774 58.64,106.088C58.239,108.31 47.624,106.675 47.763,103.733C49.197,73.169 49.635,55.375 50.062,46.585C50.154,44.713 52.36,43.957 55.215,43.952C52.432,56.85 49.593,99.788 53.065,103.033C56.793,106.536 59.704,99.721 59.854,99.361Z"
          android:strokeAlpha="0.6"
          android:fillAlpha="0.6">
        <aapt:attr name="android:fillColor">
          <gradient 
              android:startX="55.913"
              android:startY="137.253"
              android:endX="52.306"
              android:endY="76.683"
              android:type="linear">
            <item android:offset="0" android:color="#FFD900C8"/>
            <item android:offset="1" android:color="#FF976DCE"/>
          </gradient>
        </aapt:attr>
      </path>
      <path
          android:pathData="M68.499,49.501C68.438,49.789 68.304,50.098 68.098,50.411C68.098,50.411 68.072,50.463 68,50.545C66.936,51.995 64.154,53.369 58.394,52.145C54.583,51.337 52.433,50.072 51.276,48.874C50.35,47.912 50.062,46.996 50.077,46.39C50.077,46.384 50.077,46.379 50.077,46.379C50.314,44.651 52.459,43.957 55.215,43.952C60.677,43.937 68.515,46.657 68.499,49.501Z">
        <aapt:attr name="android:fillColor">
          <gradient 
              android:startX="49.967"
              android:startY="47.125"
              android:endX="68.473"
              android:endY="49.621"
              android:type="linear">
            <item android:offset="0" android:color="#FFFF4EB3"/>
            <item android:offset="0.12" android:color="#FFFF5AB9"/>
            <item android:offset="0.49" android:color="#FFFF7BCA"/>
            <item android:offset="0.79" android:color="#FFFF8ED5"/>
            <item android:offset="1" android:color="#FFFF96D9"/>
          </gradient>
        </aapt:attr>
      </path>
    </group>
  </group>
</vector>
